{
    "file_name": "corrected_CAM_20240130074328_3_warped",
    "id": 47,
    "original_width": 1024,
    "original_height": 579,
    "objects": [
        {
            "x": 1.9817073170731707,
            "y": 2.156788407262311,
            "width": 6.021341463414635,
            "height": 9.705547832680399,
            "transcription": "F-",
            "label": "terminal_number"
        },
        {
            "x": 12.347560975609756,
            "y": 2.156788407262311,
            "width": 18.445121951219512,
            "height": 11.053540587219343,
            "transcription": "A6-별03",
            "label": "terminal_number"
        },
        {
            "x": 26.82926829268293,
            "y": 85.59753991322296,
            "width": 9.756097560975608,
            "height": 6.739963772694722,
            "transcription": "행당(대)",
            "label": "terminal_number"
        },
        {
            "x": 18.75,
            "y": 90.96844854458908,
            "width": 11.28048780487805,
            "height": 9.031551455410918,
            "transcription": "별03-",
            "label": "terminal_number"
        },
        {
            "x": 0.6859756097560978,
            "y": 13.479927545389444,
            "width": 8.155487804878051,
            "height": 7.413960149964191,
            "transcription": "성동구",
            "label": "others"
        },
        {
            "x": 9.146341463414634,
            "y": 13.88432537175113,
            "width": 8.765243902439023,
            "height": 6.3355659463330385,
            "transcription": "행당동",
            "label": "others"
        },
        {
            "x": 29.95426829268293,
            "y": 92.0679051350099,
            "width": 7.393292682926823,
            "height": 5.79636884451746,
            "transcription": "이치석",
            "label": "others"
        },
        {
            "x": 29.801829268292686,
            "y": 78.31837903871268,
            "width": 8.689024390243901,
            "height": 7.144361599056396,
            "transcription": "[29/95]",
            "label": "others"
        },
        {
            "x": 66.6920731707317,
            "y": 2.291587682716205,
            "width": 4.192073170731717,
            "height": 6.06596739542525,
            "transcription": "(신)",
            "label": "others"
        },
        {
            "x": 84.90853658536585,
            "y": 2.9655840599856775,
            "width": 11.432926829268297,
            "height": 5.122372467247989,
            "transcription": "2024/01/29",
            "label": "others"
        },
        {
            "x": 50.762195121951216,
            "y": 33.56501958801971,
            "width": 9.22256097560976,
            "height": 4.043978263616843,
            "transcription": "1588-2121",
            "label": "others"
        },
        {
            "x": 43.67378048780488,
            "y": 39.361388432537176,
            "width": 19.664634146341463,
            "height": 4.313576814524623,
            "transcription": "20 년 월 일 (인)",
            "label": "others"
        },
        {
            "x": 71.41768292682927,
            "y": 47.85374278613253,
            "width": 6.25,
            "height": 4.717974640886297,
            "transcription": "일반출고",
            "label": "others"
        },
        {
            "x": 82.16463414634147,
            "y": 51.89772104974936,
            "width": 12.042682926829258,
            "height": 4.44837608997851,
            "transcription": "02-408-0010",
            "label": "others"
        },
        {
            "x": 70.19817073170732,
            "y": 52.30211887611104,
            "width": 9.756097560975604,
            "height": 3.2351826108934745,
            "transcription": "분담판교(대)",
            "label": "others"
        },
        {
            "x": 58.38414634146343,
            "y": 49.06693626521758,
            "width": 2.5152439024390247,
            "height": 7.41396014996419,
            "transcription": "수량",
            "label": "others"
        },
        {
            "x": 43.0640243902439,
            "y": 48.93213698976368,
            "width": 2.667682926829272,
            "height": 6.470365221786935,
            "transcription": "운임",
            "label": "others"
        },
        {
            "x": 43.978658536585364,
            "y": 48.93213698976368,
            "width": 4.115853658536587,
            "height": 6.335565946333041,
            "transcription": "(신)",
            "label": "others"
        },
        {
            "x": 61.12804878048781,
            "y": 50.414929019756514,
            "width": 4.496951219512191,
            "height": 4.987573191794098,
            "transcription": "1-1",
            "label": "others"
        },
        {
            "x": 0.8384146341463415,
            "y": 26.825055815324987,
            "width": 36.356707317073166,
            "height": 6.065967395425257,
            "transcription": "도매불/[캐스B]맑은소리 멀티톤블럭",
            "label": "product_name"
        },
        {
            "x": 1.0670731707317074,
            "y": 33.025822486204135,
            "width": 39.10060975609756,
            "height": 5.52677029360968,
            "transcription": "(2177) [1]/[캐스B]맑은소리 쉑쉑쉑이킹",
            "label": "product_name"
        },
        {
            "x": 0.38109756097560976,
            "y": 38.01339567799823,
            "width": 39.481707317073166,
            "height": 5.257171742701878,
            "transcription": "기로(2083) [2] / [캐스B] 맑은소리 베이비",
            "label": "product_name"
        },
        {
            "x": 0,
            "y": 42.73137031888454,
            "width": 40.015243902439025,
            "height": 6.065967395425247,
            "transcription": "마스카라 (1659) [2] / [캐스B] 맑은소리 베",
            "label": "product_name"
        },
        {
            "x": 0,
            "y": 48.3929398879481,
            "width": 39.02439024390244,
            "height": 5.931168119971353,
            "transcription": "이비탬버린(1663)[1]/[캐스B] 맑은소리",
            "label": "product_name"
        },
        {
            "x": 0,
            "y": 53.919710181557775,
            "width": 41.38719512195122,
            "height": 5.122372467247985,
            "transcription": "원목캐스터네츠(2070) [2] / [캐스B] 맑은소",
            "label": "product_name"
        },
        {
            "x": 0,
            "y": 59.58127975062134,
            "width": 2.5152439024390247,
            "height": 4.852773916340205,
            "transcription": "리",
            "label": "product_name"
        },
        {
            "x": 23.39939024390244,
            "y": 59.04208264880576,
            "width": 13.567073170731707,
            "height": 5.257171742701885,
            "transcription": "(색상랜덤) [2]",
            "label": "product_name"
        },
        {
            "x": 15.24390243902439,
            "y": 59.31168119971355,
            "width": 7.621951219512196,
            "height": 4.852773916340212,
            "transcription": "(1992)",
            "label": "product_name"
        },
        {
            "x": 44.05487804878048,
            "y": 88.56312397320862,
            "width": 53.65853658536586,
            "height": 4.987573191794098,
            "transcription": "[캐스B]맑은소리 멀티톤블럭(2177) [1]/[캐스B]맑은소리 쉑쉑쉑이",
            "label": "product_name"
        },
        {
            "x": 43.75,
            "y": 8.49235435359535,
            "width": 2.5152439024390247,
            "height": 18.063102910821854,
            "transcription": "받는분",
            "label": "recipient_key"
        },
        {
            "x": 42.14939024390244,
            "y": 58.90728337335187,
            "width": 2.5914634146341484,
            "height": 19.950292767176364,
            "transcription": "받는분",
            "label": "recipient_key"
        },
        {
            "x": 42.83536585365854,
            "y": 27.094654366232785,
            "width": 3.7347560975609753,
            "height": 3.2351826108934674,
            "transcription": "보내",
            "label": "sender_key"
        },
        {
            "x": 42.91158536585366,
            "y": 30.329836977126252,
            "width": 3.353658536585364,
            "height": 3.3699818863473534,
            "transcription": "는분",
            "label": "sender_key"
        },
        {
            "x": 41.082317073170735,
            "y": 79.8011710687055,
            "width": 4.039634146341463,
            "height": 4.987573191794098,
            "transcription": "보내",
            "label": "sender_key"
        },
        {
            "x": 41.53963414634146,
            "y": 84.51914570959181,
            "width": 3.5060975609756113,
            "height": 3.639580437255148,
            "transcription": "는분",
            "label": "sender_key"
        },
        {
            "x": 45.50304878048776,
            "y": 8.627153629049245,
            "width": 18.750000000000046,
            "height": 5.391971018155775,
            "transcription": "행당동 대림아파트",
            "label": "recipient_address_detail"
        },
        {
            "x": 64.63414634146338,
            "y": 8.357555078141447,
            "width": 19.28353658536591,
            "height": 5.526770293609663,
            "transcription": "행당동 대림아파트",
            "label": "recipient_address_detail"
        },
        {
            "x": 55.5640243902439,
            "y": 18.467500737183542,
            "width": 6.783536585365859,
            "height": 4.987573191794091,
            "transcription": "행당동",
            "label": "recipient_address_dong"
        },
        {
            "x": 66.84451219512198,
            "y": 17.92830363536789,
            "width": 16.234756097560947,
            "height": 5.122372467247975,
            "transcription": "행당동 대림아파트",
            "label": "recipient_address_detail"
        },
        {
            "x": 56.02134146341463,
            "y": 60.65967395425249,
            "width": 6.783536585365859,
            "height": 5.66156956906358,
            "transcription": "행당동",
            "label": "recipient_address_dong"
        },
        {
            "x": 67.6829268292683,
            "y": 61.33367033152197,
            "width": 17.911585365853668,
            "height": 5.391971018155779,
            "transcription": "행당동 대림아파트",
            "label": "recipient_address_dong"
        },
        {
            "x": 44.89329268292683,
            "y": 13.749526096297233,
            "width": 6.250000000000007,
            "height": 4.178777539070728,
            "transcription": "최초롱",
            "label": "recipient_name"
        },
        {
            "x": 51.37195121951211,
            "y": 13.884325371751128,
            "width": 7.16463414634154,
            "height": 3.9091789881629353,
            "transcription": "(주문자:",
            "label": "others"
        },
        {
            "x": 58.91768292682923,
            "y": 14.019124647205022,
            "width": 5.564024390243913,
            "height": 4.178777539070726,
            "transcription": "엘라즈",
            "label": "others"
        },
        {
            "x": 64.71036585365853,
            "y": 14.423522473566704,
            "width": 15.091463414634148,
            "height": 3.100383335439572,
            "transcription": "0503-5781-9485",
            "label": "recipient_phone_number"
        },
        {
            "x": 80.41158536585365,
            "y": 14.28872319811281,
            "width": 15.396341463414643,
            "height": 3.100383335439572,
            "transcription": "0503-5781-9485",
            "label": "recipient_phone_number"
        },
        {
            "x": 75.99085365853658,
            "y": 74.9483971523653,
            "width": 19.207317073170742,
            "height": 4.717974640886311,
            "transcription": "0503-5781-9485",
            "label": "recipient_phone_number"
        },
        {
            "x": 77.51524390243902,
            "y": 56.88529424154345,
            "width": 18.75,
            "height": 4.448376089978525,
            "transcription": "0503-5781-9485",
            "label": "recipient_phone_number"
        },
        {
            "x": 44.131097560975604,
            "y": 55.941699313366186,
            "width": 6.021341463414636,
            "height": 6.200766670879148,
            "transcription": "최*롱",
            "label": "recipient_name"
        },
        {
            "x": 49.92378048780488,
            "y": 56.75049496608956,
            "width": 17.911585365853647,
            "height": 4.313576814524623,
            "transcription": "(주문자: 엘라즈홈)",
            "label": "others"
        },
        {
            "x": 44.28353658536585,
            "y": 61.60326888242976,
            "width": 4.115853658536587,
            "height": 4.44837608997851,
            "transcription": "서울",
            "label": "recipient_address_do"
        },
        {
            "x": 48.47560975609756,
            "y": 61.19887105606807,
            "width": 7.012195121951223,
            "height": 5.122372467247999,
            "transcription": "성동구",
            "label": "recipient_address_gu"
        },
        {
            "x": 62.80487804878049,
            "y": 60.65967395425249,
            "width": 4.420731707317067,
            "height": 5.257171742701878,
            "transcription": "347",
            "label": "recipient_address_jibeon"
        },
        {
            "x": 85.51829268292683,
            "y": 61.064071780614185,
            "width": 6.935975609756099,
            "height": 5.79636884451746,
            "transcription": "133동",
            "label": "recipient_address_building_number"
        },
        {
            "x": 43.59756097560975,
            "y": 65.78204642150048,
            "width": 8.079268292682926,
            "height": 4.313576814524623,
            "transcription": "1504호",
            "label": "recipient_address_room_number"
        },
        {
            "x": 52.4390243902439,
            "y": 65.5124478705927,
            "width": 6.783536585365859,
            "height": 4.8527739163401975,
            "transcription": "(행당로",
            "label": "recipient_address_ro_name"
        },
        {
            "x": 59.375,
            "y": 65.37764859513881,
            "width": 4.115853658536587,
            "height": 4.58317536543241,
            "transcription": "9길",
            "label": "recipient_address_gil_name"
        },
        {
            "x": 63.262195121951216,
            "y": 64.83845149332322,
            "width": 3.963414634146339,
            "height": 6.335565946333034,
            "transcription": "43)",
            "label": "recipient_address_ro_number"
        },
        {
            "x": 44.05487804878049,
            "y": 79.9359703441594,
            "width": 11.051829268292678,
            "height": 4.1787775390707225,
            "transcription": "한국교육시스템",
            "label": "sender_name"
        },
        {
            "x": 65.70121951219512,
            "y": 79.8011710687055,
            "width": 13.033536585365866,
            "height": 4.717974640886297,
            "transcription": "031-698-3867",
            "label": "sender_phone_number"
        },
        {
            "x": 44.207317073170735,
            "y": 84.7887442604996,
            "width": 3.2774390243902403,
            "height": 3.639580437255148,
            "transcription": "경기",
            "label": "sender_address_do"
        },
        {
            "x": 47.5609756097561,
            "y": 84.6539449850457,
            "width": 5.030487804878042,
            "height": 4.178777539070737,
            "transcription": "성남시",
            "label": "sender_address_si"
        },
        {
            "x": 52.89634146341463,
            "y": 83.84514933232235,
            "width": 5.335365853658537,
            "height": 4.717974640886297,
            "transcription": "분당구",
            "label": "sender_address_gu"
        },
        {
            "x": 58.15548780487805,
            "y": 84.11474788323012,
            "width": 5.564024390243901,
            "height": 4.987573191794098,
            "transcription": "궁내동",
            "label": "sender_address_dong"
        },
        {
            "x": 62.95731707317073,
            "y": 84.7887442604996,
            "width": 8.155487804878064,
            "height": 3.774379712709049,
            "transcription": "301-8 4",
            "label": "sender_address_jibeon"
        },
        {
            "x": 70.88414634146342,
            "y": 84.24954715868402,
            "width": 11.661585365853654,
            "height": 4.1787775390707225,
            "transcription": "주건축물제1동",
            "label": "sender_address_detail"
        },
        {
            "x": 82.54573170731707,
            "y": 84.24954715868402,
            "width": 8.46036585365853,
            "height": 4.717974640886297,
            "transcription": "대왕판교로",
            "label": "sender_address_ro_name"
        },
        {
            "x": 90.70121951219512,
            "y": 83.97994860777624,
            "width": 5.182926829268297,
            "height": 4.58317536543241,
            "transcription": "361번",
            "label": "sender_address_gil_name"
        },
        {
            "x": 41.53963414634146,
            "y": 94.6290913686339,
            "width": 3.0487804878048763,
            "height": 4.043978263616836,
            "transcription": "비고",
            "label": "delivery_message_key"
        },
        {
            "x": 41.08231707317072,
            "y": 89.91111672774758,
            "width": 3.429878048780495,
            "height": 3.9091789881629353,
            "transcription": "품명`",
            "label": "product_name_key"
        },
        {
            "x": 79.80182926829268,
            "y": 47.71894351067863,
            "width": 14.786585365853668,
            "height": 4.31357681452463,
            "transcription": "2471-3790-9550",
            "label": "tracking_number"
        },
        {
            "x": 49.16158536585371,
            "y": 3.235182610893465,
            "width": 17.073170731707275,
            "height": 4.852773916340194,
            "transcription": "2471-3790-9550",
            "label": "tracking_number"
        },
        {
            "x": 44.05487804878047,
            "y": 3.1003833354395707,
            "width": 5.9451219512195275,
            "height": 4.043978263616833,
            "transcription": "운송장번호",
            "label": "tracking_number_key"
        },
        {
            "x": 43.06402439024388,
            "y": 43.944563797969586,
            "width": 6.5548780487805045,
            "height": 4.717974640886302,
            "transcription": "운송장번호",
            "label": "tracking_number_key"
        },
        {
            "x": 48.01829268292683,
            "y": 44.34896162433127,
            "width": 17.835365853658537,
            "height": 5.122372467247992,
            "transcription": "2471-3790-9550",
            "label": "tracking_number"
        },
        {
            "x": 42.83536585365854,
            "y": 33.69981886347361,
            "width": 7.698170731707322,
            "height": 5.257171742701878,
            "transcription": "록데택배",
            "label": "company_name"
        },
        {
            "x": 44.81707317073172,
            "y": 28.038249294410043,
            "width": 13.109756097560968,
            "height": 4.583175365432409,
            "transcription": "한국교육시스템/",
            "label": "sender_name"
        },
        {
            "x": 57.92682926829268,
            "y": 27.90345001895615,
            "width": 14.100609756097555,
            "height": 5.122372467247985,
            "transcription": "031-698-3867",
            "label": "sender_phone_number"
        },
        {
            "x": 83.53658536585365,
            "y": 18.197902186275748,
            "width": 5.868902439024396,
            "height": 4.7179746408863075,
            "transcription": "133동",
            "label": "recipient_address_building_number"
        },
        {
            "x": 84.375,
            "y": 9.031551455410927,
            "width": 6.25,
            "height": 4.448376089978517,
            "transcription": "133동",
            "label": "recipient_address_building_number"
        },
        {
            "x": 91.08231707317073,
            "y": 8.896752179957032,
            "width": 5.792682926829272,
            "height": 4.4483760899785185,
            "transcription": "1504",
            "label": "recipient_address_room_number"
        },
        {
            "x": 89.71036585365853,
            "y": 18.197902186275748,
            "width": 6.631097560975618,
            "height": 5.391971018155779,
            "transcription": "1504호",
            "label": "recipient_address_room_number"
        },
        {
            "x": 62.80487804878049,
            "y": 17.793504359914063,
            "width": 3.7347560975609824,
            "height": 5.122372467247988,
            "transcription": "347",
            "label": "recipient_address_jibeon"
        },
        {
            "x": 45.5030487804878,
            "y": 17.793504359914063,
            "width": 4.039634146341463,
            "height": 4.7179746408863075,
            "transcription": "서울",
            "label": "recipient_address_do"
        },
        {
            "x": 49.69512195121951,
            "y": 18.19790218627575,
            "width": 6.326219512195124,
            "height": 3.7743797127090417,
            "transcription": "성동구",
            "label": "recipient_address_gu"
        },
        {
            "x": 56.09756097560976,
            "y": 22.107081174438687,
            "width": 3.7347560975609753,
            "height": 4.313576814524623,
            "transcription": "43)",
            "label": "recipient_address_ro_number"
        },
        {
            "x": 52.362804878048784,
            "y": 21.8374826235309,
            "width": 3.048780487804869,
            "height": 4.852773916340201,
            "transcription": "9길",
            "label": "recipient_address_gil_name"
        },
        {
            "x": 45.88414634146341,
            "y": 22.24188044989258,
            "width": 6.478658536585371,
            "height": 4.44837608997852,
            "transcription": "(행당로",
            "label": "recipient_address_ro_name"
        }
    ]
}