{
    "file_name": "corrected_CAM_20231004105925_1_warped",
    "id": 18,
    "original_width": 985,
    "original_height": 553,
    "objects": [
        {
            "x": 5.624256513171636,
            "y": 2.3255813953488373,
            "width": 5.122090753067026,
            "height": 6.440071556350626,
            "transcription": "F-",
            "label": "terminal_number"
        },
        {
            "x": 14.763673347075542,
            "y": 1.073345259391771,
            "width": 14.964539651117391,
            "height": 8.22898032200358,
            "transcription": "A6-별01",
            "label": "terminal_number"
        },
        {
            "x": 5.423390209129791,
            "y": 9.838998211091235,
            "width": 8.536817921778376,
            "height": 7.3345259391771,
            "transcription": "성동구",
            "label": "recipient_address_gu"
        },
        {
            "x": 14.663240195054621,
            "y": 10.196779964221825,
            "width": 8.436384769757451,
            "height": 6.97674418604651,
            "transcription": "행당동",
            "label": "recipient_address_dong"
        },
        {
            "x": 1.2051978242510646,
            "y": 20.930232558139537,
            "width": 6.9298874894436215,
            "height": 4.83005366726297,
            "transcription": "주문번호",
            "label": "others"
        },
        {
            "x": 8.637251073799296,
            "y": 19.499105545617173,
            "width": 8.838117377841142,
            "height": 5.724508050089444,
            "transcription": "101337569",
            "label": "others"
        },
        {
            "x": 1.1047646722301427,
            "y": 26.654740608228984,
            "width": 39.068496136138684,
            "height": 5.008944543828264,
            "transcription": "여성 페이크 포켓 폴로 티...[421B1T0052_BK/1] /1개",
            "label": "product_name"
        },
        {
            "x": 0.7030320641464545,
            "y": 59.92844364937389,
            "width": 7.833785857631921,
            "height": 5.366726296958845,
            "transcription": "M3039",
            "label": "others"
        },
        {
            "x": 32.74120755882059,
            "y": 61.18067978533095,
            "width": 7.733352705610997,
            "height": 5.187835420393554,
            "transcription": "총수량 1개",
            "label": "others"
        },
        {
            "x": 0.6025989121255323,
            "y": 66.54740608228981,
            "width": 10.043315202092206,
            "height": 3.398926654740606,
            "transcription": "운송장번호",
            "label": "tracking_number_key"
        },
        {
            "x": 10.947213570280505,
            "y": 66.3685152057245,
            "width": 14.96453965111739,
            "height": 3.577817531305911,
            "transcription": "3133-1023-0170",
            "label": "tracking_number"
        },
        {
            "x": 0.30129945606276615,
            "y": 70.6618962432916,
            "width": 8.938550529862063,
            "height": 3.398926654740606,
            "transcription": "보내는 분",
            "label": "sender_key"
        },
        {
            "x": 9.440716289966673,
            "y": 70.30411449016101,
            "width": 12.353277698573415,
            "height": 3.756708407871187,
            "transcription": "(주) 크리스 F&C",
            "label": "sender_name"
        },
        {
            "x": 0.20089940192161188,
            "y": 74.4186046511628,
            "width": 7.231186945506388,
            "height": 3.0411449016100107,
            "transcription": "받는 분",
            "label": "recipient_key"
        },
        {
            "x": 7.6329195535900745,
            "y": 73.91944746894488,
            "width": 17.174068995577667,
            "height": 3.719192960393194,
            "transcription": "최우리(주문자: 최우리)",
            "label": "recipient_name"
        },
        {
            "x": 0.2008663040418441,
            "y": 77.99642218246869,
            "width": 5.423390209129792,
            "height": 3.041144901610025,
            "transcription": "주소:",
            "label": "others"
        },
        {
            "x": 6.126422273276246,
            "y": 78.35420393559929,
            "width": 3.8164597767950372,
            "height": 3.2200357781753155,
            "transcription": "서울",
            "label": "recipient_address_do"
        },
        {
            "x": 10.445047810175895,
            "y": 78.35420393559929,
            "width": 4.6199249929624155,
            "height": 3.398926654740606,
            "transcription": "성동구",
            "label": "recipient_address_gu"
        },
        {
            "x": 15.366272259201075,
            "y": 78.175313059034,
            "width": 6.729021185401777,
            "height": 3.7567084078712014,
            "transcription": "행당 2동",
            "label": "recipient_address_dong"
        },
        {
            "x": 22.296159748644698,
            "y": 77.4597495527728,
            "width": 7.8337858576319235,
            "height": 4.293381037567087,
            "transcription": "한진아파트",
            "label": "recipient_address_detail"
        },
        {
            "x": 30.431245062339386,
            "y": 76.20751341681574,
            "width": 4.820791297004256,
            "height": 4.293381037567087,
            "transcription": "202동",
            "label": "recipient_address_building_number"
        },
        {
            "x": 35.85463527146918,
            "y": 76.02862254025044,
            "width": 5.6242565131716304,
            "height": 4.651162790697683,
            "transcription": "2107호",
            "label": "recipient_address_room_number"
        },
        {
            "x": 0.4017326080836882,
            "y": 81.7531305903399,
            "width": 5.122090753067025,
            "height": 3.398926654740606,
            "transcription": "운임:",
            "label": "others"
        },
        {
            "x": 6.528154881359933,
            "y": 81.7531305903399,
            "width": 4.820791297004259,
            "height": 3.577817531305911,
            "transcription": "신용",
            "label": "others"
        },
        {
            "x": 26.514352133523424,
            "y": 86.58318425760287,
            "width": 11.04764672230143,
            "height": 6.261180679785326,
            "transcription": "행당(대)",
            "label": "terminal_number"
        },
        {
            "x": 26.11261952543973,
            "y": 93.38103756708398,
            "width": 8.17187315288007,
            "height": 6.587212802768576,
            "transcription": "별01-",
            "label": "terminal_number"
        },
        {
            "x": 33.94640538307166,
            "y": 93.73881932021467,
            "width": 8.235518465715607,
            "height": 5.5456171735241355,
            "transcription": "이형국",
            "label": "others"
        },
        {
            "x": 44.446308491850296,
            "y": 1.8985345645929568,
            "width": 6.1719670288146276,
            "height": 4.004864362061785,
            "transcription": "운송장번호",
            "label": "tracking_number_key"
        },
        {
            "x": 51.522206986733025,
            "y": 1.8437216651229544,
            "width": 17.618231812218387,
            "height": 4.417459014662378,
            "transcription": "3133-1023-0170",
            "label": "tracking_number"
        },
        {
            "x": 74.11966619144049,
            "y": 1.7081120533663143,
            "width": 5.012313960101962,
            "height": 4.731959502984317,
            "transcription": "신용",
            "label": "others"
        },
        {
            "x": 84.57094309557912,
            "y": 1.4859399119923637,
            "width": 12.045749148547923,
            "height": 4.4174590146623816,
            "transcription": "2023/09/26",
            "label": "others"
        },
        {
            "x": 44.19370143618708,
            "y": 7.383573021316432,
            "width": 1.9082298883975213,
            "height": 18.067978533094806,
            "transcription": "받는 분",
            "label": "recipient_key"
        },
        {
            "x": 46.57976743342932,
            "y": 6.797853309481217,
            "width": 6.829454337422704,
            "height": 5.187835420393559,
            "transcription": "성동구",
            "label": "recipient_address_gu"
        },
        {
            "x": 54.16091313751824,
            "y": 6.7545720446725594,
            "width": 8.612921422539392,
            "height": 5.236882502532893,
            "transcription": "행당2동",
            "label": "recipient_address_dong"
        },
        {
            "x": 62.97158631711813,
            "y": 6.976744186046512,
            "width": 12.152411394531576,
            "height": 5.008944543828264,
            "transcription": "한진아파트",
            "label": "recipient_address_detail"
        },
        {
            "x": 46.40011623366599,
            "y": 12.522361359570661,
            "width": 4.7203581449833365,
            "height": 3.041144901610018,
            "transcription": "최유리",
            "label": "recipient_name"
        },
        {
            "x": 51.42177383471207,
            "y": 12.343470483005362,
            "width": 6.327288577318094,
            "height": 3.9471309190978436,
            "transcription": "(주문자:",
            "label": "recipient_name"
        },
        {
            "x": 57.77027751630869,
            "y": 11.985688729874772,
            "width": 6.08399206471922,
            "height": 4.1693030604717976,
            "transcription": "최유리",
            "label": "recipient_name"
        },
        {
            "x": 64.27721729339012,
            "y": 12.880143112701253,
            "width": 13.658908674845392,
            "height": 3.398926654740608,
            "transcription": "0504-2193-8388",
            "label": "tracking_number"
        },
        {
            "x": 78.53872488036106,
            "y": 12.343470483005367,
            "width": 16.87276953951489,
            "height": 3.398926654740608,
            "transcription": "0504-2193-8388",
            "label": "tracking_number"
        },
        {
            "x": 75.62616347175432,
            "y": 6.97674418604651,
            "width": 6.783909581884309,
            "height": 4.83005366726297,
            "transcription": "202동",
            "label": "recipient_address_building_number"
        },
        {
            "x": 82.75691726523978,
            "y": 6.440071556350627,
            "width": 8.838117377841144,
            "height": 5.187835420393559,
            "transcription": "2107호",
            "label": "recipient_address_room_number"
        },
        {
            "x": 46.600982537707836,
            "y": 15.92128801431127,
            "width": 3.3142940166904253,
            "height": 4.651162790697676,
            "transcription": "서울",
            "label": "recipient_address_do"
        },
        {
            "x": 50.31700916248195,
            "y": 16.27906976744186,
            "width": 5.021657601046101,
            "height": 4.11449016100179,
            "transcription": "성동구",
            "label": "recipient_address_gu"
        },
        {
            "x": 55.73728482463037,
            "y": 15.92128801431127,
            "width": 5.825122817213476,
            "height": 4.651162790697676,
            "transcription": "행당2동",
            "label": "recipient_address_dong"
        },
        {
            "x": 62.24111005473044,
            "y": 16.143460155685236,
            "width": 8.643480167762045,
            "height": 3.8490367548191835,
            "transcription": "한진아파트",
            "label": "recipient_address_detail"
        },
        {
            "x": 71.43852983209823,
            "y": 16.100178890876567,
            "width": 4.820791297004263,
            "height": 3.7567084078711983,
            "transcription": "202동",
            "label": "recipient_name"
        },
        {
            "x": 76.42962868792169,
            "y": 16.100178890876553,
            "width": 6.421492635376261,
            "height": 4.102958526340454,
            "transcription": "2107호",
            "label": "recipient_address_room_number"
        },
        {
            "x": 43.88928743314294,
            "y": 26.654740608228984,
            "width": 2.711695104564896,
            "height": 2.504472271914132,
            "transcription": "보내",
            "label": "sender_key"
        },
        {
            "x": 43.88928743314294,
            "y": 30.05366726296959,
            "width": 2.0086630404184405,
            "height": 2.504472271914132,
            "transcription": "는분",
            "label": "sender_key"
        },
        {
            "x": 45.9983836255823,
            "y": 28.80143112701252,
            "width": 11.683918926630989,
            "height": 3.398926654740612,
            "transcription": "(주)크리스탈FC /",
            "label": "sender_name"
        },
        {
            "x": 57.648629260009265,
            "y": 28.980322003577818,
            "width": 8.637251073799284,
            "height": 3.7567084078711943,
            "transcription": "1670-2807",
            "label": "sender_phone_number"
        },
        {
            "x": 44.190586889205704,
            "y": 33.810375670840784,
            "width": 7.3316200975273205,
            "height": 4.11449016100179,
            "transcription": "롯데택배",
            "label": "others"
        },
        {
            "x": 51.619525591772565,
            "y": 33.810375670840784,
            "width": 9.340283137945754,
            "height": 3.935599284436492,
            "transcription": "1588-2121",
            "label": "others"
        },
        {
            "x": 44.09015373718475,
            "y": 38.819320214669034,
            "width": 19.663095967231143,
            "height": 4.076974713523829,
            "transcription": "20   년   월   일   (인)",
            "label": "others"
        },
        {
            "x": 44.090153737184785,
            "y": 42.93381037567084,
            "width": 6.025989121255321,
            "height": 5.545617173524157,
            "transcription": "운송장번호",
            "label": "tracking_number_key"
        },
        {
            "x": 50.71874177056564,
            "y": 43.112701252236135,
            "width": 18.58013312387058,
            "height": 4.11449016100179,
            "transcription": "3133-1023-0170",
            "label": "tracking_number"
        },
        {
            "x": 73.81836673537772,
            "y": 46.51162790697674,
            "width": 5.7246896651925425,
            "height": 5.366726296958852,
            "transcription": "일반출고",
            "label": "others"
        },
        {
            "x": 81.85301889705147,
            "y": 46.332737030411444,
            "width": 14.060641282929097,
            "height": 5.187835420393569,
            "transcription": "3133-1023-0170",
            "label": "tracking_number"
        },
        {
            "x": 44.09018683506456,
            "y": 49.37388193202147,
            "width": 2.5108288005230506,
            "height": 6.440071556350624,
            "transcription": "운임",
            "label": "others"
        },
        {
            "x": 47.50488090589614,
            "y": 49.73166368515206,
            "width": 5.222523905087947,
            "height": 5.54561717352415,
            "transcription": "신용",
            "label": "others"
        },
        {
            "x": 59.355992844364934,
            "y": 49.19499105545617,
            "width": 2.0086630404184476,
            "height": 7.1556350626118075,
            "transcription": "수량",
            "label": "others"
        },
        {
            "x": 63.373318925201815,
            "y": 50.089445438282645,
            "width": 3.213860864669499,
            "height": 4.830053667262973,
            "transcription": "1",
            "label": "others"
        },
        {
            "x": 68.99757543837346,
            "y": 51.699463327370296,
            "width": 4.519491840941498,
            "height": 4.114490161001797,
            "transcription": "집화점",
            "label": "others"
        },
        {
            "x": 43.98972058516386,
            "y": 59.570661896243294,
            "width": 2.0086630404184405,
            "height": 20.751341681574246,
            "transcription": "받는 분",
            "label": "recipient_key"
        },
        {
            "x": 46.09881677760321,
            "y": 56.17173524150266,
            "width": 5.191965159865329,
            "height": 4.293381037567072,
            "transcription": "최우리",
            "label": "recipient_name"
        },
        {
            "x": 51.33632669300694,
            "y": 55.63506261180679,
            "width": 6.412735719023269,
            "height": 4.521318996271721,
            "transcription": "(주문자:",
            "label": "recipient_name"
        },
        {
            "x": 57.767162969327316,
            "y": 55.77643804089415,
            "width": 5.91056995891865,
            "height": 4.830053667262982,
            "transcription": "최우리)",
            "label": "recipient_name"
        },
        {
            "x": 46.40011623366602,
            "y": 60.32374084998246,
            "width": 4.8239058439856155,
            "height": 5.508101726046142,
            "transcription": "서울",
            "label": "recipient_address_do"
        },
        {
            "x": 51.72307329077485,
            "y": 59.983256548843876,
            "width": 7.063993933668549,
            "height": 5.577366803671466,
            "transcription": "성동구",
            "label": "recipient_address_gu"
        },
        {
            "x": 59.45642599638583,
            "y": 59.74955277280859,
            "width": 8.582362677316786,
            "height": 5.984195638941375,
            "transcription": "행당2동",
            "label": "recipient_address_dong"
        },
        {
            "x": 68.99757543837346,
            "y": 59.21288014311271,
            "width": 11.428164226106597,
            "height": 6.440071556350632,
            "transcription": "한진아파트",
            "label": "recipient_address_detail"
        },
        {
            "x": 80.84868737684225,
            "y": 58.497316636851515,
            "width": 6.729021185401791,
            "height": 7.334525939177105,
            "transcription": "202동",
            "label": "recipient_address_building_number"
        },
        {
            "x": 87.97944117032772,
            "y": 57.78175313059034,
            "width": 9.139416833903923,
            "height": 7.692307692307686,
            "transcription": "2107호",
            "label": "recipient_address_room_number"
        },
        {
            "x": 77.7352596641937,
            "y": 75.54676281002457,
            "width": 16.23961188216672,
            "height": 3.880786384966474,
            "transcription": "0504-2193-8388",
            "label": "tracking_number"
        },
        {
            "x": 43.688421129101094,
            "y": 82.82647584973166,
            "width": 2.611261952543977,
            "height": 2.86225402504472,
            "transcription": "보내",
            "label": "sender_key"
        },
        {
            "x": 43.48755482505925,
            "y": 86.40429338103756,
            "width": 2.5108288005230506,
            "height": 2.3255813953488484,
            "transcription": "는분",
            "label": "sender_key"
        },
        {
            "x": 43.88928743314294,
            "y": 90.51878354203936,
            "width": 2.309962496481205,
            "height": 4.1144901610017826,
            "transcription": "품목",
            "label": "product_name"
        },
        {
            "x": 43.48755482505925,
            "y": 95.8855098389982,
            "width": 2.4103956485021314,
            "height": 3.398926654740606,
            "transcription": "비고",
            "label": "delivery_message_key"
        },
        {
            "x": 46.50054938568691,
            "y": 95.34883720930233,
            "width": 13.458042370803554,
            "height": 3.5778175313058966,
            "transcription": "배송메시지: 경비실",
            "label": "delivery_message"
        },
        {
            "x": 46.70141568972876,
            "y": 89.80322003577818,
            "width": 40.97672602453619,
            "height": 4.6511627906976685,
            "transcription": "여성 페이크 포켓 폴러 티...[421B1T0052_BK/1] /1개",
            "label": "tracking_number"
        },
        {
            "x": 46.50058248356668,
            "y": 81.03756708407872,
            "width": 11.851111938468804,
            "height": 3.577817531305896,
            "transcription": "(주)크리스탈F&C",
            "label": "sender_name"
        },
        {
            "x": 71.70927054293837,
            "y": 79.9699876420176,
            "width": 9.735786652066688,
            "height": 3.9298334671057984,
            "transcription": "1670-2807",
            "label": "sender_phone_number"
        },
        {
            "x": 46.04392838112069,
            "y": 85.01644763332386,
            "width": 2.9674498050892955,
            "height": 4.428990649323706,
            "transcription": "경기",
            "label": "sender_address_do"
        },
        {
            "x": 49.31267764227273,
            "y": 85.1520572450805,
            "width": 5.322957057108866,
            "height": 4.293381037567087,
            "transcription": "이천시",
            "label": "sender_address_si"
        },
        {
            "x": 54.535168449480906,
            "y": 84.79427549194992,
            "width": 5.322957057108866,
            "height": 4.293381037567073,
            "transcription": "파장면",
            "label": "sender_address_myeon"
        },
        {
            "x": 60.36032436457415,
            "y": 84.0787119856887,
            "width": 4.875679693486783,
            "height": 4.786772402454359,
            "transcription": "덕평로",
            "label": "sender_address_ro_name"
        },
        {
            "x": 65.07756796257611,
            "y": 84.48554082095863,
            "width": 6.226855425297174,
            "height": 4.293381037567087,
            "transcription": "733-20",
            "label": "sender_address_ro_number"
        },
        {
            "x": 72.01056999900112,
            "y": 84.61538461538461,
            "width": 15.56713856324292,
            "height": 3.7567084078712014,
            "transcription": "크리스탈F&C 물류센터",
            "label": "sender_name"
        }
    ]
}